MANIFEST.in
README.TXT
README.md
README.rst
acknowledgements.txt
setup.py
PyBrain2.egg-info/PKG-INFO
PyBrain2.egg-info/SOURCES.txt
PyBrain2.egg-info/dependency_links.txt
PyBrain2.egg-info/requires.txt
PyBrain2.egg-info/top_level.txt
pybrain2/__init__.py
pybrain2/utilities.py
pybrain2/auxiliary/__init__.py
pybrain2/auxiliary/gaussprocess.py
pybrain2/auxiliary/gradientdescent.py
pybrain2/auxiliary/importancemixing.py
pybrain2/auxiliary/kmeans.py
pybrain2/auxiliary/pca.py
pybrain2/datasets/__init__.py
pybrain2/datasets/classification.py
pybrain2/datasets/dataset.py
pybrain2/datasets/importance.py
pybrain2/datasets/reinforcement.py
pybrain2/datasets/sequential.py
pybrain2/datasets/supervised.py
pybrain2/datasets/unsupervised.py
pybrain2/optimization/__init__.py
pybrain2/optimization/hillclimber.py
pybrain2/optimization/neldermead.py
pybrain2/optimization/optimizer.py
pybrain2/optimization/randomsearch.py
pybrain2/optimization/distributionbased/__init__.py
pybrain2/optimization/distributionbased/cmaes.py
pybrain2/optimization/distributionbased/distributionbased.py
pybrain2/optimization/distributionbased/fem.py
pybrain2/optimization/distributionbased/nes.py
pybrain2/optimization/distributionbased/rank1.py
pybrain2/optimization/distributionbased/snes.py
pybrain2/optimization/distributionbased/ves.py
pybrain2/optimization/distributionbased/xnes.py
pybrain2/optimization/finitedifference/__init__.py
pybrain2/optimization/finitedifference/fd.py
pybrain2/optimization/finitedifference/pgpe.py
pybrain2/optimization/finitedifference/spsa.py
pybrain2/optimization/memetic/__init__.py
pybrain2/optimization/memetic/innerinversememetic.py
pybrain2/optimization/memetic/innermemetic.py
pybrain2/optimization/memetic/inversememetic.py
pybrain2/optimization/memetic/memetic.py
pybrain2/optimization/populationbased/__init__.py
pybrain2/optimization/populationbased/es.py
pybrain2/optimization/populationbased/evolution.py
pybrain2/optimization/populationbased/ga.py
pybrain2/optimization/populationbased/pso.py
pybrain2/optimization/populationbased/coevolution/__init__.py
pybrain2/optimization/populationbased/coevolution/coevolution.py
