Metadata-Version: 1.0
Name: PyBrain2
Version: 0.4.0
Summary: PyBrain2 is the modestly improved PyBrain, the Swiss army knife for neural networking.
Home-page: http://github.com/pybrain2/
Author: Hobson Lane <pybrain2@totalgood.com> and Chris Morgan <chris.j.morgan@gmail.com>
Author-email: pybrain2@totalgood.com
License: BSD
Keywords: Neural Network Machine Learning
Platform: UNKNOWN
